{
  "project_info": {
    "project_number": "370093279174",
    "project_id": "velocittmerchant",
    "storage_bucket": "velocittmerchant.appspot.com"
  },
  "client": [
    {
      "client_info": {
        "mobilesdk_app_id": "1:370093279174:android:da774a1f2cc47e822214c7",
        "android_client_info": {
          "package_name": "com.codeelan.velocit_merchant"
        }
      },
      "oauth_client": [
        {
          "client_id": "370093279174-rjudfvlfbhfksdu5qej09ds5baots52b.apps.googleusercontent.com",
          "client_type": 3
        }
      ],
      "api_key": [
        {
          "current_key": "AIzaSyD25ZHJewLVfDkyWxQVFD_LaH9-fkK61To"
        }
      ],
      "services": {
        "appinvite_service": {
          "other_platform_oauth_client": [
            {
              "client_id": "370093279174-rjudfvlfbhfksdu5qej09ds5baots52b.apps.googleusercontent.com",
              "client_type": 3
            }
          ]
        }
      }
    }
  ],
  "configuration_version": "1"
}